{
    "title":"GPRS C SDK DOC",
    "description": "GPRS C SDK 文档",
    "author":"Ai-Thinker",
    "language": "zh-hans",
    "root":".",
    "plugins": [
        "github",
        "splitter",
        "fontsettings",
        "-search",
        "search-pro",
        "edit-link",
        "page-toc-button",
        "sharing",
        "my-toolbar"
    ],
    "pluginsConfig": {
        "github": {
            "url": "https://github.com/Ai-Thinker-Open/GPRS_C_SDK_DOC"
        },
        "search-pro": {
            "cutWordLib": "nodejieba",
            "defineWord" : ["Gitbook Use"]
        },
        "simple-page-toc": {
            "maxDepth": 4,
            "skipFirstH1": false
        },
        "edit-link": {
            "base": "https://github.com/Ai-Thinker-Open/GPRS_C_SDK_DOC/blob/master",
            "label": ""
        },
        "page-toc-button": {
            "maxTocDepth": 2,
            "minTocSize": 2
        },
        "sharing": {
            "weibo": true,
            "facebook": true,
            "twitter": true,
            "google": false,
            "instapaper": false,
            "vk": false,
            "all": [
                "weibo",
                "facebook",
                "twitter",
                "google",
                "instapaper",
                "vk"
            ]
        },
        "my-toolbar": {
            "buttons": [
                {
                    "label": "English",
                    "text":"English",
                    "icon": "fa fa-language",
                    "position": "left",
                    "target": "_self",
                    "url": "https://ai-thinker-open.github.io/GPRS_C_SDK_DOC/en"
                }
            ]
        },
        "fontsettings": {
            "theme": "white",
            "family": "sans", 
            "size": 2 
        }
    }
}